perceiver/__init__.py
perceiver/data/__init__.py
perceiver/data/audio/__init__.py
perceiver/data/audio/giantmidi_piano.py
perceiver/data/audio/maestro_v3.py
perceiver/data/audio/midi_processor.py
perceiver/data/audio/symbolic.py
perceiver/data/audio/utils.py
perceiver/data/text/__init__.py
perceiver/data/text/bookcorpus.py
perceiver/data/text/bookcorpusopen.py
perceiver/data/text/c4.py
perceiver/data/text/collator.py
perceiver/data/text/common.py
perceiver/data/text/enwik8.py
perceiver/data/text/imdb.py
perceiver/data/text/utils.py
perceiver/data/text/wikipedia.py
perceiver/data/text/wikitext.py
perceiver/data/vision/__init__.py
perceiver/data/vision/common.py
perceiver/data/vision/imagenet.py
perceiver/data/vision/mnist.py
perceiver/data/vision/optical_flow.py
perceiver/data/vision/video_utils.py
perceiver/model/__init__.py
perceiver/model/audio/__init__.py
perceiver/model/audio/symbolic/__init__.py
perceiver/model/audio/symbolic/backend.py
perceiver/model/audio/symbolic/huggingface.py
perceiver/model/audio/symbolic/lightning.py
perceiver/model/core/__init__.py
perceiver/model/core/adapter.py
perceiver/model/core/classifier.py
perceiver/model/core/config.py
perceiver/model/core/huggingface.py
perceiver/model/core/lightning.py
perceiver/model/core/modules.py
perceiver/model/core/position.py
perceiver/model/core/utils.py
perceiver/model/text/__init__.py
perceiver/model/text/classifier/__init__.py
perceiver/model/text/classifier/backend.py
perceiver/model/text/classifier/huggingface.py
perceiver/model/text/classifier/lightning.py
perceiver/model/text/clm/__init__.py
perceiver/model/text/clm/backend.py
perceiver/model/text/clm/huggingface.py
perceiver/model/text/clm/lightning.py
perceiver/model/text/common/__init__.py
perceiver/model/text/common/backend.py
perceiver/model/text/common/huggingface.py
perceiver/model/text/mlm/__init__.py
perceiver/model/text/mlm/backend.py
perceiver/model/text/mlm/huggingface.py
perceiver/model/text/mlm/lightning.py
perceiver_io-0.11.0.dist-info/LICENSE
perceiver_io-0.11.0.dist-info/WHEEL
perceiver_io-0.11.0.dist-info/METADATA
perceiver_io-0.11.0.dist-info/RECORD
