Metadata-Version: 2.1
Name: perceiver-io
Version: 0.11.0
Summary: Perceiver IO
Home-page: https://github.com/krasserm/perceiver-io
License: Apache-2.0
Keywords: perceiver-io,perceiver-ar,deep-learning
Author: Martin Krasser
Author-email: krasserm@googlemail.com
Requires-Python: >=3.8,<3.11
Classifier: Development Status :: 4 - Beta
Classifier: Environment :: Console
Classifier: Intended Audience :: Developers
Classifier: License :: OSI Approved :: Apache Software License
Classifier: Natural Language :: English
Classifier: Operating System :: OS Independent
Classifier: Programming Language :: Python :: 3
Classifier: Programming Language :: Python :: 3.8
Classifier: Programming Language :: Python :: 3.9
Classifier: Programming Language :: Python :: 3.10
Classifier: Programming Language :: Python :: 3
Classifier: Topic :: Scientific/Engineering
Classifier: Topic :: Scientific/Engineering :: Artificial Intelligence
Provides-Extra: audio
Provides-Extra: text
Provides-Extra: vision
Requires-Dist: cchardet (>=2.1,<3.0)
Requires-Dist: datasets (>=2.4,<3.0); extra == "text" or extra == "vision" or extra == "audio"
Requires-Dist: einops (>=0.4,<0.5)
Requires-Dist: fairscale (>=0.4,<0.5)
Requires-Dist: fsspec[s3]
Requires-Dist: jsonargparse[signatures] (>=4.18,<5.0)
Requires-Dist: opencv-python (>=4.6.0.66,<5.0.0.0); extra == "vision"
Requires-Dist: pretty_midi (>=0.2.10,<0.3.0); extra == "audio"
Requires-Dist: pytorch-lightning (>=2.0,<3.0)
Requires-Dist: tensorboard (>=2.11,<3.0)
Requires-Dist: tokenizers (>=0.12,<0.13); extra == "text"
Requires-Dist: torch (>=2.0,<3.0)
Requires-Dist: torch-optimizer (>=0.3,<0.4)
Requires-Dist: torchmetrics (>=0.9,<0.10)
Requires-Dist: torchvision (>=0.15,<0.16); extra == "vision"
Requires-Dist: transformers (>=4.28,<5.0); extra == "text" or extra == "audio"
